{"textures":{"0":"hockey:icon/arrow-up","particle":"hockey:icon/flashee"},"elements":[{"from":[0, 1, 0],"to":[16, 2, 16],"faces":{"north":{"uv":[0, 0, 16, 1],"texture":"#missing"},"east":{"uv":[0, 0, 16, 1],"texture":"#missing"},"south":{"uv":[0, 0, 16, 1],"texture":"#missing"},"west":{"uv":[0, 0, 16, 1],"texture":"#missing"},"up":{"uv":[0, 0, 16, 16],"texture":"#0"},"down":{"uv":[0, 0, 16, 16],"texture":"#missing"}}}],"gui_light":"front","display":{"gui":{"rotation":[90, 0, 0],"translation":[-44.75, 0.03, 0]}}}